setup.py
vststaskcmd/__init__.py
vststaskcmd/build.py
vststaskcmd/task.py
vststaskcmd.egg-info/PKG-INFO
vststaskcmd.egg-info/SOURCES.txt
vststaskcmd.egg-info/dependency_links.txt
vststaskcmd.egg-info/not-zip-safe
vststaskcmd.egg-info/top_level.txt