Metadata-Version: 1.0
Name: vststaskcmd
Version: 0.1.0
Summary: A simple wrapper for using VSTS task commands
Home-page: UNKNOWN
Author: UNKNOWN
Author-email: UNKNOWN
License: MIT
Platform: UNKNOWN
